lifx/__init__.py
lifx/api.py
lifx/color.py
lifx/const.py
lifx/exceptions.py
lifx/py.typed
lifx/animation/__init__.py
lifx/animation/animator.py
lifx/animation/framebuffer.py
lifx/animation/orientation.py
lifx/animation/packets.py
lifx/devices/__init__.py
lifx/devices/base.py
lifx/devices/ceiling.py
lifx/devices/hev.py
lifx/devices/infrared.py
lifx/devices/light.py
lifx/devices/matrix.py
lifx/devices/multizone.py
lifx/effects/__init__.py
lifx/effects/base.py
lifx/effects/colorloop.py
lifx/effects/conductor.py
lifx/effects/const.py
lifx/effects/models.py
lifx/effects/pulse.py
lifx/effects/state_manager.py
lifx/network/__init__.py
lifx/network/connection.py
lifx/network/discovery.py
lifx/network/message.py
lifx/network/transport.py
lifx/network/utils.py
lifx/network/mdns/__init__.py
lifx/network/mdns/discovery.py
lifx/network/mdns/dns.py
lifx/network/mdns/transport.py
lifx/network/mdns/types.py
lifx/products/__init__.py
lifx/products/generator.py
lifx/products/quirks.py
lifx/products/registry.py
lifx/protocol/__init__.py
lifx/protocol/base.py
lifx/protocol/generator.py
lifx/protocol/header.py
lifx/protocol/models.py
lifx/protocol/packets.py
lifx/protocol/protocol_types.py
lifx/protocol/serializer.py
lifx/theme/__init__.py
lifx/theme/canvas.py
lifx/theme/generators.py
lifx/theme/library.py
lifx/theme/theme.py
lifx_async-5.1.0.dist-info/METADATA
lifx_async-5.1.0.dist-info/WHEEL
lifx_async-5.1.0.dist-info/licenses/LICENSE
lifx_async-5.1.0.dist-info/RECORD
