Metadata-Version: 2.4
Name: lifx-async
Version: 5.1.0
Summary: A modern, type-safe, async Python library for controlling LIFX lights
Author-email: Avi Miller <me@dje.li>
Maintainer-email: Avi Miller <me@dje.li>
License-Expression: UPL-1.0
License-File: LICENSE
Classifier: Framework :: AsyncIO
Classifier: Framework :: Pytest
Classifier: Intended Audience :: Developers
Classifier: Natural Language :: English
Classifier: Operating System :: OS Independent
Classifier: Programming Language :: Python :: 3.10
Classifier: Programming Language :: Python :: 3.11
Classifier: Programming Language :: Python :: 3.12
Classifier: Programming Language :: Python :: 3.13
Classifier: Programming Language :: Python :: 3.14
Classifier: Topic :: Software Development :: Libraries
Classifier: Topic :: Software Development :: Libraries :: Python Modules
Classifier: Typing :: Typed
Requires-Python: >=3.10
